simpleccx/__init__.py
simpleccx/calculix.py
simpleccx/frdreader.py
simpleccx/simpleccx.py
simpleccx/templates/__init__.py
simpleccx/templates/model.fbd.j2
simpleccx/templates/model.inp.j2
simpleccx/templates/post.fbd.j2
simpleccx-0.0.9.dist-info/LICENSE
simpleccx-0.0.9.dist-info/METADATA
simpleccx-0.0.9.dist-info/WHEEL
simpleccx-0.0.9.dist-info/top_level.txt
simpleccx-0.0.9.dist-info/RECORD
