Metadata-Version: 2.2
Name: simpleccx
Version: 0.0.9
Summary: A simple package to perform FE analysis of extruded sections using the CalculiX solver
Author-email: Ronald Grefhorst <ronald@rgde.be>
Project-URL: Homepage, https://github.com/Grefron/simpleccx
Project-URL: Issues, https://github.com/Grefron/simpleccx/issues
Classifier: Programming Language :: Python :: 3
Classifier: License :: OSI Approved :: MIT License
Classifier: Operating System :: OS Independent
Requires-Python: >=3.8
License-File: LICENSE
Requires-Dist: jinja2
Requires-Dist: pandas
Requires-Dist: pillow
